py_mockserver-0.1.6.dist-info/METADATA
py_mockserver-0.1.6.dist-info/RECORD
py_mockserver-0.1.6.dist-info/WHEEL
py_mockserver-0.1.6.dist-info/top_level.txt
pymockserver/__init__.py
pymockserver/client.py
pymockserver/forward.py
pymockserver/request.py
pymockserver/response.py
pymockserver/times.py
tests/__init__.py
tests/client_test.py
tests/forward_test.py
tests/integration_test.py
tests/request_test.py
tests/response_test.py
tests/times_test.py
