Metadata-Version: 2.1
Name: py-mockserver
Version: 0.1.6
Summary: Python client for mockserver
Home-page: https://github.com/danggrianto/py-mockserver
Author: Daniel Anggrianto
Author-email: d.anggrianto@gmail.com
License: UNKNOWN
Platform: UNKNOWN
Classifier: Programming Language :: Python :: 3
Classifier: License :: OSI Approved :: MIT License
Classifier: Operating System :: OS Independent
Requires-Dist: requests
